{
	"animations": [
		{
			"loop": false,
			"offsets": [
				0,
				0
			],
			"anim": "idle",
			"fps": 24,
			"name": "idle",
			"indices": []
		},
		{
			"loop": false,
			"offsets": [
				4,
				-1
			],
			"anim": "singLEFT",
			"fps": 24,
			"name": "right",
			"indices": []
		},
		{
			"loop": false,
			"offsets": [
				5,
				-1
			],
			"anim": "singDOWN",
			"fps": 24,
			"name": "down",
			"indices": []
		},
		{
			"loop": false,
			"offsets": [
				5,
				-2
			],
			"anim": "singUP",
			"fps": 24,
			"name": "up",
			"indices": []
		},
		{
			"loop": false,
			"offsets": [
				4,
				-2
			],
			"anim": "singRIGHT",
			"fps": 24,
			"name": "left",
			"indices": []
		},
		{
			"loop": false,
			"offsets": [
				1,
				2
			],
			"anim": "singLEFTmiss",
			"fps": 24,
			"name": "missright",
			"indices": []
		},
		{
			"loop": false,
			"offsets": [
				5,
				11
			],
			"anim": "singDOWNmiss",
			"fps": 24,
			"name": "missdown",
			"indices": []
		},
		{
			"loop": false,
			"offsets": [
				-1,
				4
			],
			"anim": "singUPmiss",
			"fps": 24,
			"name": "missup",
			"indices": []
		},
		{
			"loop": false,
			"offsets": [
				6,
				2
			],
			"anim": "singRIGHTmiss",
			"fps": 24,
			"name": "missleft",
			"indices": []
		},
		{
			"offsets": [
				0,
				0
			],
			"loop": false,
			"fps": 12,
			"anim": "intro",
			"indices": [],
			"name": "intro"
		},
		{
			"loop": false,
			"offsets": [
				0,
				0
			],
			"anim": "yeah!",
			"fps": 12,
			"name": "yeah",
			"indices": []
		}
	],
	"vocals_file": "",
	"no_antialiasing": false,
	"image": "characters/BOYFRIENDsunk",
	"position": [
		-70,
		190
	],
	"healthicon": "bf",
	"flip_x": true,
	"healthbar_colors": [
		49,
		176,
		209
	],
	"camera_position": [
		320,
		100
	],
	"sing_duration": 4,
	"scale": 0.9,
	"_editor_isPlayer": true
}